secret/__init__.py
secret/test.py
testsupersecret-20.10.post1.dist-info/METADATA
testsupersecret-20.10.post1.dist-info/WHEEL
testsupersecret-20.10.post1.dist-info/top_level.txt
testsupersecret-20.10.post1.dist-info/RECORD
