Metadata-Version: 2.1
Name: testsupersecret
Version: 20.10.post1
Summary: testing pip version 3
Home-page: UNKNOWN
Author: Ondrej
Author-email: UNKNOWN
License: UNKNOWN
Platform: UNKNOWN
